infrahub_testcontainers/__init__.py
infrahub_testcontainers/constants.py
infrahub_testcontainers/container.py
infrahub_testcontainers/docker-compose-cluster.test.yml
infrahub_testcontainers/docker-compose.test.yml
infrahub_testcontainers/haproxy.cfg
infrahub_testcontainers/helpers.py
infrahub_testcontainers/host.py
infrahub_testcontainers/measurements.py
infrahub_testcontainers/models.py
infrahub_testcontainers/performance_test.py
infrahub_testcontainers/plugin.py
infrahub_testcontainers/prometheus.yml
infrahub_testcontainers-1.6.1.dist-info/METADATA
infrahub_testcontainers-1.6.1.dist-info/WHEEL
infrahub_testcontainers-1.6.1.dist-info/entry_points.txt
infrahub_testcontainers-1.6.1.dist-info/RECORD
