Metadata-Version: 2.4
Name: infrahub-testcontainers
Version: 1.6.1
Summary: Testcontainers instance for Infrahub to easily build integration tests
Project-URL: Homepage, https://opsmill.com
Project-URL: Repository, https://github.com/opsmill/infrahub
Author-email: OpsMill <info@opsmill.com>
License-Expression: Apache-2.0
Classifier: Intended Audience :: Developers
Classifier: Programming Language :: Python :: 3
Classifier: Programming Language :: Python :: 3.10
Classifier: Programming Language :: Python :: 3.11
Classifier: Programming Language :: Python :: 3.12
Classifier: Programming Language :: Python :: 3.13
Classifier: Programming Language :: Python :: 3.14
Requires-Python: >=3.10
Requires-Dist: httpx<0.28
Requires-Dist: prefect-client==3.5.0
Requires-Dist: psutil
Requires-Dist: pydantic<3,>=2.10.6
Requires-Dist: pytest
Requires-Dist: testcontainers<4.9,>=4.8
